cat_fact/__init__.py
cat_fact/cli.py
cat_fact/client.py
cat_fact-0.2.0.dist-info/LICENSE
cat_fact-0.2.0.dist-info/METADATA
cat_fact-0.2.0.dist-info/WHEEL
cat_fact-0.2.0.dist-info/entry_points.txt
cat_fact-0.2.0.dist-info/top_level.txt
cat_fact-0.2.0.dist-info/RECORD
