Metadata-Version: 2.1
Name: cat-fact
Version: 0.2.0
Summary: Get random cat facts fromt the internet 😸
Home-page: https://github.com/sohail535/cat_fact
Author: Shaik Sohail Yunus
Author-email: sohail.yunusha1@gmail.com
Maintainer: Shaik Sohail Yunus
Maintainer-email: sohail.yunusha1@gmail.com
License: UNKNOWN
Platform: UNKNOWN
Requires-Dist: click (>=6.7)
Requires-Dist: requests (>=2.21)
